pypi_sql_query_inspector/__init__.py
pypi_sql_query_inspector/middleware.py
pypi_sql_query_inspector-1.0.3.dist-info/LICENSE
pypi_sql_query_inspector-1.0.3.dist-info/METADATA
pypi_sql_query_inspector-1.0.3.dist-info/WHEEL
pypi_sql_query_inspector-1.0.3.dist-info/top_level.txt
pypi_sql_query_inspector-1.0.3.dist-info/RECORD
