Metadata-Version: 2.1
Name: pypi-sql-query-inspector
Version: 1.0.3
Summary: A django middleware package to print out connection queries in terminal when DEBUGing
Author: peacefulseeker
Project-URL: Homepage, https://pypi.org/project/pypi-sql-query-inspector/
Requires-Python: >=3.7
License-File: LICENSE
Requires-Dist: Pygments (<=2.14.0)
Requires-Dist: sqlparse (>=0.4.3)
